moonblade/__init__.py
moonblade/logger.py
moonblade/moonblade.py
moonblade/router.py
moonblade/utils.py
moonblade-1.1.5.dist-info/LICENSE
moonblade-1.1.5.dist-info/METADATA
moonblade-1.1.5.dist-info/WHEEL
moonblade-1.1.5.dist-info/top_level.txt
moonblade-1.1.5.dist-info/RECORD
