Metadata-Version: 2.2
Name: moonblade
Version: 1.1.5
Summary: An asynchronous Python 3 library designed to communicate with the LOL server via the LCU API in a simple and flexible way.
Home-page: https://github.com/gfk-sveyigey/moonblade
Author: gfk-sveyigey
Author-email: gfk_sveyigey@163.com
License: MIT
Classifier: Development Status :: 4 - Beta
Classifier: License :: OSI Approved :: MIT License
Classifier: Operating System :: Microsoft :: Windows :: Windows 10
Classifier: Operating System :: Microsoft :: Windows :: Windows 11
Classifier: Programming Language :: Python :: 3
Classifier: Programming Language :: Python :: 3 :: Only
License-File: LICENSE
Requires-Dist: httpx
Requires-Dist: psutil
Requires-Dist: websockets
Dynamic: author
Dynamic: author-email
Dynamic: classifier
Dynamic: description
Dynamic: description-content-type
Dynamic: home-page
Dynamic: license
Dynamic: requires-dist
Dynamic: summary
